pgdbpy
