Metadata-Version: 1.0
Name: pgdbpy
Version: 1.0.7
Summary: A simple PostgreSQL database connection manager that exploits the power of cfgpy
Home-page: https://github.com/phenicle/pgdbpy
Author: Phenicle
Author-email: pheniclebeefheart@gmail.com
License: Mozilla Public License 2.0 (MPL 2.0)
Platform: UNKNOWN
